roverlib/__init__.py
roverlib/bootinfo.py
roverlib/callbacks.py
roverlib/configuration.py
roverlib/index.py
roverlib/py.typed
roverlib/rovercom.py
roverlib/streams.py
roverlib-2.0.0.dist-info/METADATA
roverlib-2.0.0.dist-info/WHEEL
roverlib-2.0.0.dist-info/licenses/LICENSE
roverlib-2.0.0.dist-info/RECORD
