Metadata-Version: 2.4
Name: roverlib
Version: 2.0.0
Summary: ASE roverlib
Project-URL: Repository, https://github.com/vu-ase/roverlib-python
Project-URL: Issues, https://github.com/vu-ase/roverlib-python/issues
Author-email: NielsD1 <n.j.dijkstra@student.vu.nl>, maxgallup <m.gallup@student.vu.nl>
License-File: LICENSE
Requires-Python: >=3.10
Requires-Dist: betterproto
Requires-Dist: loguru
Requires-Dist: pyzmq
